aws_helpers/__init__.py
aws_helpers/lambda/__init__.py
aws_helpers/s3/__init__.py
aws_helpers/s3/client.py
aws_helpers/s3/download.py
aws_helpers/s3/list.py
aws_helpers/s3/upload.py
aws_helpers/sqs/__init__.py
aws_helpers/sqs/client.py
aws_helpers/sqs/receive.py
aws_helpers/sqs/send.py
mongo_helpers/__init__.py
mongo_helpers/aggregation/__init__.py
mongo_helpers/aggregation/aggregation.py
mongo_helpers/client/__init__.py
mongo_helpers/client/close_mongo_client.py
mongo_helpers/client/get_mongo_client.py
mongo_helpers/crud/__init__.py
mongo_helpers/crud/bulk.py
mongo_helpers/crud/delete_document.py
mongo_helpers/crud/find_document.py
mongo_helpers/crud/get_document.py
mongo_helpers/crud/insert_document.py
mongo_helpers/crud/update_document.py
mongo_helpers/indexing/__init__.py
mongo_helpers/indexing/indexing.py
mongo_helpers/README.md
mongo_helpers/validate/__init__.py
mongo_helpers/validate/validate_document.py
typesense_helpers/__init__.py
typesense_helpers/client/__init__.py
typesense_helpers/client/initialize.py
typesense_helpers/collection/__init__.py
typesense_helpers/collection/create.py
typesense_helpers/collection/delete.py
typesense_helpers/collection/export.py
typesense_helpers/collection/import_documents.py
typesense_helpers/collection/search.py
typesense_helpers/crud/__init__ copy.py
typesense_helpers/crud/__init__.py
typesense_helpers/document/indexing.py
typesense_helpers/document/search.py
utils/__init__.py
utils/csv/append.py
utils/csv/read.py
utils/csv/write.py
utils/html/fetch_html.py
utils/html/parse_html.py
utils/json/append.py
utils/json/csv.py
utils/json/pandas_dataframe.py
utils/json/print.py
utils/json/read.py
utils/json/write.py
utils/re/validations.py
utils/selenium/browser_console.logs.py
utils/selenium/browser_tabs.py
utils/selenium/browser_window.py
utils/selenium/cookies.py
utils/selenium/downlaod.py
utils/selenium/html.py
utils/selenium/screeshot.py
utils/selenium/simulate_keyboard.py
utils/selenium/simulate_mouse.py
helpers_python-0.1.0.dist-info/METADATA
helpers_python-0.1.0.dist-info/WHEEL
helpers_python-0.1.0.dist-info/RECORD
